{
	"id": "Hul3hkyGHEny9WE",
	"json": "{\"id\":\"Hul3hkyGHEny9WE\",\"url\":\"https://www.wedding-spot.com/venue/13580/angelos-677-prime/\",\"loadedUrl\":\"https://www.wedding-spot.com/venue/13580/angelos-677-prime/\",\"uniqueKey\":\"https://www.wedding-spot.com/venue/13580/angelos-677-prime\",\"method\":\"GET\",\"noRetry\":false,\"retryCount\":0,\"errorMessages\":[],\"headers\":{},\"userData\":{\"label\":\"VENUE_DETAIL\",\"__crawlee\":{\"state\":4}},\"handledAt\":\"2025-06-28T09:56:32.922Z\"}",
	"method": "GET",
	"orderNo": null,
	"retryCount": 0,
	"uniqueKey": "https://www.wedding-spot.com/venue/13580/angelos-677-prime",
	"url": "https://www.wedding-spot.com/venue/13580/angelos-677-prime/"
}