{
	"id": "zXQ54hcDFXSJ2PW",
	"json": "{\"id\":\"zXQ54hcDFXSJ2PW\",\"url\":\"https://www.wedding-spot.com/venue/14639/yale-manor-at-copper-beeches/\",\"loadedUrl\":\"https://www.wedding-spot.com/venue/14639/yale-manor-at-copper-beeches/\",\"uniqueKey\":\"https://www.wedding-spot.com/venue/14639/yale-manor-at-copper-beeches\",\"method\":\"GET\",\"noRetry\":false,\"retryCount\":0,\"errorMessages\":[],\"headers\":{},\"userData\":{\"label\":\"VENUE_DETAIL\",\"__crawlee\":{\"state\":4}},\"handledAt\":\"2025-06-26T22:07:09.882Z\"}",
	"method": "GET",
	"orderNo": null,
	"retryCount": 0,
	"uniqueKey": "https://www.wedding-spot.com/venue/14639/yale-manor-at-copper-beeches",
	"url": "https://www.wedding-spot.com/venue/14639/yale-manor-at-copper-beeches/"
}